source_appsflyer/__init__.py
source_appsflyer/fields/__init__.py
source_appsflyer/fields/additional_fields.py
source_appsflyer/fields/mapper.py
source_appsflyer/run.py
source_appsflyer/schemas/daily_report.json
source_appsflyer/schemas/geo_events_report.json
source_appsflyer/schemas/geo_report.json
source_appsflyer/schemas/in_app_events.json
source_appsflyer/schemas/installs.json
source_appsflyer/schemas/organic_in_app_events.json
source_appsflyer/schemas/organic_installs.json
source_appsflyer/schemas/organic_uninstall_events.json
source_appsflyer/schemas/partners_events_report.json
source_appsflyer/schemas/partners_report.json
source_appsflyer/schemas/retargeting_daily_report.json
source_appsflyer/schemas/retargeting_geo_events_report.json
source_appsflyer/schemas/retargeting_geo_report.json
source_appsflyer/schemas/retargeting_in_app_events.json
source_appsflyer/schemas/retargeting_installs.json
source_appsflyer/schemas/retargeting_partners_events_report.json
source_appsflyer/schemas/retargeting_partners_report.json
source_appsflyer/schemas/uninstall_events.json
source_appsflyer/source.py
source_appsflyer/spec.json
airbyte_source_appsflyer-0.2.40.dist-info/METADATA
airbyte_source_appsflyer-0.2.40.dist-info/WHEEL
airbyte_source_appsflyer-0.2.40.dist-info/entry_points.txt
airbyte_source_appsflyer-0.2.40.dist-info/RECORD
